pywikibot_extensions/__init__.py
pywikibot_extensions/page.py
pywikibot_extensions/py.typed
pywikibot_extensions/textlib.py
pywikibot_extensions-24.9.21.dist-info/LICENSE
pywikibot_extensions-24.9.21.dist-info/METADATA
pywikibot_extensions-24.9.21.dist-info/WHEEL
pywikibot_extensions-24.9.21.dist-info/RECORD
